{
  "VahidOOnLine": 239687,
  "mwarmonitor": 8959,
  "pm_afshaa": 90614,
  "iaghapour": 2601,
  "DEJradio": 4590,
  "mamlekate": 103512,
  "VahidOnline": 75427,
  "kianmeli1": 87362,
  "IranIntlTV": 336806,
  "FoxNewsChannel": 3,
  "Shin_Persian": 5963,
  "Iliaen": 4434,
  "CnnBrk": 247615,
  "reutersworldchannel": 151524,
  "ManotoTV": 105343,
  "FarsiVOA": 217522,
  "DW_Farsi": 124590,
  "Persian_Trend_Official": 13975,
  "RadioFarda": 157089,
  "IranianMinds": 20003,
  "BBCPersian": 280845,
  "IranWire": 65,
  "idfinfarsi": 11564,
  "Dirty_Kids": 389311,
  "Hranews": 112899,
  "officialrezapahlavi": 1828,
  "configx2ray": 38663,
  "manototv": 105343,
  "alonews": 119481,
  "farsi_fox_news": 89200,
  "FoxNewsTwitter": 341572,
  "CNNfarsiCHANNEL": 51273,
  "WithYashar": 11052
}